tiny_openai/__init__.py
tiny_openai/embedder.py
tiny_openai/llm.py
tiny_openai/register.py
tiny_openai/utils.py
tinygent_openai-0.1.1007.dist-info/METADATA
tinygent_openai-0.1.1007.dist-info/WHEEL
tinygent_openai-0.1.1007.dist-info/entry_points.txt
tinygent_openai-0.1.1007.dist-info/RECORD
