Metadata-Version: 2.4
Name: tinygent-openai
Version: 0.1.1007
Requires-Dist: langchain-core>=0.3.74
Requires-Dist: openai>=1.101.0
Requires-Dist: tiktoken>=0.12.0
Requires-Dist: tinygent
